diskbackup.py
diskbackup-0.0.4.dist-info/LICENSE
diskbackup-0.0.4.dist-info/METADATA
diskbackup-0.0.4.dist-info/WHEEL
diskbackup-0.0.4.dist-info/top_level.txt
diskbackup-0.0.4.dist-info/RECORD
