Metadata-Version: 2.1
Name: diskbackup
Version: 0.0.4
Summary: Simple backup tool
Home-page: https://github.com/josephernest/diskbackup
Author: Joseph Ernest
Author-email: nouvellecollection@gmail.com
License: MIT
Platform: any
Classifier: Programming Language :: Python :: 3
Classifier: Operating System :: OS Independent
Requires-Python: >=3.6
